texthub/Model.py
texthub/Text.py
texthub/__init__.py
texthub/filter.py
texthub-0.1.0.dist-info/LICENSE
texthub-0.1.0.dist-info/METADATA
texthub-0.1.0.dist-info/WHEEL
texthub-0.1.0.dist-info/top_level.txt
texthub-0.1.0.dist-info/RECORD
