Metadata-Version: 2.1
Name: texthub
Version: 0.1.0
Summary: A Python library that provides a simple interface to use NLP models
Home-page: https://github.com/Keycatowo/text-hub
Author: owo
Author-email: contact@owomail.cc
Classifier: Programming Language :: Python :: 3
Classifier: License :: OSI Approved :: MIT License
Classifier: Operating System :: OS Independent
License-File: LICENSE
Requires-Dist: pandas
Requires-Dist: bidict
Requires-Dist: transformers
Requires-Dist: torch
